[
    {
        "id":"1",
        "title":"Güveç Soya Soslu Tavuk",
        "price":40,
        "about":"",
        "image":""
    },
    {
        "id":"2",
        "title":"Güveç Köri Soslu Tavuk",
        "price":40,
        "about":"",
        "image":""
    },
    {
        "id":"3",
        "title":"Güveç Kremalı Tavuk",
        "price":40,
        "about":"",
        "image":""
    },
    {
        "id":"4",
        "title":"Güveç Barbekü Soslu Tavuk",
        "price":40,
        "about":"",
        "image":""
    },
    {
        "id":"5",
        "title":"Güveç Ballı Hardallı Tavuk",
        "price":40,
        "about":"",
        "image":""
    },
    {
        "id":"6",
        "title":"Güveç Meksika Soslu Tavuk",
        "price":40,
        "about":"",
        "image":""
    },
    {
        "id":"8",
        "title":"Güveç Kaşarlı Mantar",
        "price":40,
        "about":"",
        "image":""
    },
    {
        "id":"9",
        "title":"Güveç Mantar Soslu Tavuk",
        "price":40,
        "about":"",
        "image":""
    },
    {
        "id":"10",
        "title":"Izgara Tavuk",
        "price":40,
        "about":"Patates ve salata ile servis edilir.",
        "image":""
    },
    {
        "id":"11",
        "title":"Özel Soslu Izgara Tavuk",
        "price":38,
        "about":"Karamelize mantar ve özel krema sos ile salata ve patates ile servis edilir.",
        "image":""
    },
    {
        "id":"12",
        "title":"Şinitzel",
        "price":37,
        "about":"Patates ve salata ile servis edilir.",
        "image":""
    },
    {
        "id":"13",
        "title":"Güveç Soslu Köfte",
        "price":42,
        "about":"Özel krema sos ile servis edilir.",
        "image":""
    },
    {
        "id":"14",
        "title":"Köfte Tabağı",
        "price":40,
        "about":"Patates ve salata ile servis edilir.",
        "image":""
    },
    {
        "id":"15",
        "title":"Karışık Izgara",
        "price":45,
        "about":"3 adet köfte ve 1 adet ızgara tavuk, salata ve patates ile servis edilir.",
        "image":""
    },
    {
        "id":"16",
        "title":"Tavuk Quasedilla",
        "price":42,
        "about":"Patates ile servis edilir.",
        "image":""
    },
    {
        "id":"17",
        "title":"Köfte Quasedilla",
        "price":50,
        "about":"Patates ile servis edilir.",
        "image":""
    }

]