[
    {
        "id":"1",
        "title":"Yeşillik Salata",
        "price":24,
        "about":"Kıvırcık, atom, roka, nane, cherry domates",
        "image":"https://images2.imgbox.com/d0/cb/kuRX3Bci_o.jpg"
    },
    {
        "id":"2",
        "title":"Peynirli Salata",
        "price":30,
        "about":"Kıvırcık, domates, salatalık, çeçil peynir, beyaz peynir, kaşar peynir, cheddar peynir",
        "image":"https://images2.imgbox.com/cb/72/Z6uOHEnA_o.jpg"
    },
    {
        "id":"3",
        "title":"Tavuklu Salata",
        "price":36,
        "about":"Kıvırcık, roka, tavuk, cherry domates, mısır",
        "image":"https://images2.imgbox.com/5f/82/mZPlpe8y_o.jpg"
    },
    {
        "id":"4",
        "title":"Ton Balıklı Salata",
        "price":37,
        "about":"Kıvırcık , roka, nane, domates, mısır, ton balığı",
        "image":"https://images2.imgbox.com/0d/a9/GalB2BDj_o.jpg"
    },
    {
        "id":"5",
        "title":"Çıtır Tavuk Salata",
        "price":38,
        "about":"Kıvırcık , domates, çıtır paneli kemiksiz tavuk parçaları, mısır",
        "image":"https://images2.imgbox.com/a8/24/fbMqvyaz_o.jpg"
    }
]